omni_sync/__init__.py
omni_sync/cli.py
omni_sync/config.py
omni_sync/main.py
omni_sync/models.py
omni_sync/api/__init__.py
omni_sync/api/omni_client.py
omni_sync/data_sources/__init__.py
omni_sync/data_sources/base.py
omni_sync/data_sources/csv_source.py
omni_sync/data_sources/json_source.py
omni_sync/utils/__init__.py
omni_sync/utils/logger.py
omni_user_manager-0.2.4.dist-info/licenses/LICENSE
omni_user_manager-0.2.4.dist-info/METADATA
omni_user_manager-0.2.4.dist-info/WHEEL
omni_user_manager-0.2.4.dist-info/entry_points.txt
omni_user_manager-0.2.4.dist-info/top_level.txt
omni_user_manager-0.2.4.dist-info/RECORD
