Metadata-Version: 2.4
Name: omni-user-manager
Version: 0.2.4
Summary: Omni User Manager - Sync users and groups with Omni
Home-page: https://github.com/Hawkfry-Group/omni-user-manager
Author: Jamie Fry
Author-email: jamie@hawkfry.com
Classifier: Development Status :: 4 - Beta
Classifier: Intended Audience :: Developers
Classifier: License :: OSI Approved :: MIT License
Classifier: Programming Language :: Python :: 3
Classifier: Programming Language :: Python :: 3.9
Classifier: Programming Language :: Python :: 3.10
Classifier: Programming Language :: Python :: 3.11
Classifier: Programming Language :: Python :: 3.12
Requires-Python: >=3.9
License-File: LICENSE
Requires-Dist: requests
Requires-Dist: python-dotenv
Dynamic: author
Dynamic: author-email
Dynamic: classifier
Dynamic: description
Dynamic: description-content-type
Dynamic: home-page
Dynamic: license-file
Dynamic: requires-dist
Dynamic: requires-python
Dynamic: summary
